openbd/__init__.py
openbd/__main__.py
openbd-0.3.0.dist-info/LICENSE
openbd-0.3.0.dist-info/METADATA
openbd-0.3.0.dist-info/WHEEL
openbd-0.3.0.dist-info/entry_points.txt
openbd-0.3.0.dist-info/RECORD
